mosheh/__init__.py
mosheh/codebase.py
mosheh/constants.py
mosheh/main.py
mosheh/py.typed
mosheh/utils.py
mosheh/commands/__init__.py
mosheh/commands/create_cmd.py
mosheh/commands/init_cmd.py
mosheh/commands/update_cmd.py
mosheh/doc/__init__.py
mosheh/doc/create.py
mosheh/doc/shared.py
mosheh/doc/update.py
mosheh/handlers/__init__.py
mosheh/handlers/py.typed
mosheh/handlers/python.py
mosheh/types/__init__.py
mosheh/types/basic.py
mosheh/types/contracts.py
mosheh/types/enums.py
mosheh/types/jsoncfg.py
mosheh-2.0.4.dist-info/METADATA
mosheh-2.0.4.dist-info/WHEEL
mosheh-2.0.4.dist-info/entry_points.txt
mosheh-2.0.4.dist-info/licenses/LICENSE
mosheh-2.0.4.dist-info/RECORD
