Metadata-Version: 2.4
Name: mosheh
Version: 2.0.4
Summary: Mosheh, automatic and elegant documentation of Python code with MkDocs.
Project-URL: Documentation, https://lucasgoncsilva.github.io/mosheh/
Project-URL: Repository, https://github.com/lucasGoncSilva/mosheh/
Project-URL: Issues, https://github.com/LucasGoncSilva/mosheh/issues
Project-URL: Changelog, https://github.com/LucasGoncSilva/mosheh/blob/main/.github/CHANGELOG.md
Author-email: LucasGonc <lucasgoncsilva04@gmail.com>
Maintainer-email: LucasGonc <lucasgoncsilva04@gmail.com>
License: MIT License
License-File: LICENSE
Keywords: CLI,MkDocs,Python,automation,documentation,generation
Requires-Python: >=3.12
Requires-Dist: mkdocs-git-revision-date-localized-plugin>=1.4.7
Requires-Dist: mkdocs-material-extensions>=1.3.1
Requires-Dist: mkdocs-material>=9.6.16
Requires-Dist: mkdocs>=1.6.1
Requires-Dist: pyyaml>=6.0.2
Requires-Dist: rich>=14.1.0
Requires-Dist: stdlib-list>=0.11.1
